sezer/__init__.py
sezer/sezer.py
sezer-0.1.dist-info/LICENSE
sezer-0.1.dist-info/METADATA
sezer-0.1.dist-info/WHEEL
sezer-0.1.dist-info/top_level.txt
sezer-0.1.dist-info/RECORD
