Metadata-Version: 2.1
Name: sezer
Version: 0.1
Summary: Sezer's swiss army knife
Home-page: https://github.com/Natgho/sezer
Author: Adınız
Author-email: email@example.com
Classifier: Programming Language :: Python :: 3
Classifier: License :: OSI Approved :: MIT License
Classifier: Operating System :: OS Independent
Requires-Python: >=3.6
License-File: LICENSE
